{
  "player_data": {
    "Name": "Player",
    "Money": "500"
  },
  "soap": {
    "upgradesUnlocked": false,
    "foundryUnlocked": false
  },
  "upgrades": [
    {
      "upgradesKey": 0,
      "count": 0,
      "unlocked": false
    },
    {
      "upgradesKey": 1,
      "count": 0,
      "unlocked": true
    },
    {
      "upgradesKey": 2,
      "count": 0,
      "unlocked": true
    },
    {
      "upgradesKey": 3,
      "count": 0,
      "unlocked": false
    },
    {
      "upgradesKey": 4,
      "count": 0,
      "unlocked": false
    },
    {
      "upgradesKey": 5,
      "count": 0,
      "unlocked": false
    },
    {
      "upgradesKey": 6,
      "count": 0,
      "unlocked": false
    },
    {
      "upgradesKey": 7,
      "count": 0,
      "unlocked": false
    },
    {
      "upgradesKey": 8,
      "count": 0,
      "unlocked": false
    }
  ],
  "generator": {
    "Generators": [
      {
        "generatorsKey": 0,
        "count": 0,
        "unlocked": false
      },
      {
        "generatorsKey": 1,
        "count": 0,
        "unlocked": false
      }
    ]
  },
  "Red Soap producer": {
    "eatenUnlocked": false,
    "decelerateUnlocked": false
  },
  "Red Soap": {
    "SpeedCount": 0,
    "QualityCount": 0,
    "Unlocked": true,
    "Tier": 0,
    "DecelerateCount": 0
  }
}
